{
	"name": "cowelKeyCard",
	"plugin-id": "Sprite",
	"sid": 798061758130861,
	"isGlobal": false,
	"instanceVariables": [],
	"behaviorTypes": [],
	"effectTypes": [],
	"animations": {
		"items": [
			{
				"frames": [
					{
						"width": 267,
						"height": 152,
						"originX": 0.473612529792305,
						"originY": 1.856907894736842,
						"originalSource": "",
						"exportFormat": "png",
						"exportQuality": 0.8,
						"imageSpriteId": 8121320,
						"collisionPoly": {
							"points": [
								0,
								0,
								0.473612529792305,
								0,
								1,
								0,
								1,
								1,
								0.609805924412666,
								1,
								0.473612529792305,
								1,
								0.30337078651685395,
								1,
								0,
								1
							]
						},
						"useCollisionPoly": true,
						"duration": 1
					}
				],
				"sid": 860354382303247,
				"name": "Animation 1",
				"isLooping": false,
				"isPingPong": false,
				"repeatCount": 1,
				"repeatTo": 0,
				"speed": 5
			}
		],
		"subfolders": []
	}
}